ComputerGraphicsFromScratch/README.md
ComputerGraphicsFromScratch/__init__.py
ComputerGraphicsFromScratch/__main__.py
ComputerGraphicsFromScratch/file.epub
ComputerGraphicsFromScratch/index.html
ComputerGraphicsFromScratch/css/__init__.py
ComputerGraphicsFromScratch/css/annotations.css
ComputerGraphicsFromScratch/css/main.css
ComputerGraphicsFromScratch/css/normalize.css
ComputerGraphicsFromScratch/css/popup.css
ComputerGraphicsFromScratch/font/__init__.py
ComputerGraphicsFromScratch/font/fontello.eot
ComputerGraphicsFromScratch/font/fontello.svg
ComputerGraphicsFromScratch/font/fontello.ttf
ComputerGraphicsFromScratch/font/fontello.woff
ComputerGraphicsFromScratch/img/__init__.py
ComputerGraphicsFromScratch/img/annotator-glyph-sprite.png
ComputerGraphicsFromScratch/img/annotator-icon-sprite.png
ComputerGraphicsFromScratch/img/apple-touch-icon.png
ComputerGraphicsFromScratch/img/cancelfullscreen.png
ComputerGraphicsFromScratch/img/close.png
ComputerGraphicsFromScratch/img/fullscreen.png
ComputerGraphicsFromScratch/img/loader.gif
ComputerGraphicsFromScratch/img/menu-icon.png
ComputerGraphicsFromScratch/img/save.png
ComputerGraphicsFromScratch/img/saved.png
ComputerGraphicsFromScratch/img/settings-s.png
ComputerGraphicsFromScratch/img/settings.png
ComputerGraphicsFromScratch/img/star.png
ComputerGraphicsFromScratch/js/__init__.py
ComputerGraphicsFromScratch/js/epub.js
ComputerGraphicsFromScratch/js/epub.min.js
ComputerGraphicsFromScratch/js/epub.min.map
ComputerGraphicsFromScratch/js/hooks.min.js
ComputerGraphicsFromScratch/js/hooks.min.map
ComputerGraphicsFromScratch/js/reader.js
ComputerGraphicsFromScratch/js/reader.js.map
ComputerGraphicsFromScratch/js/reader.min.js
ComputerGraphicsFromScratch/js/reader.min.map
ComputerGraphicsFromScratch/js/hooks/__init__.py
ComputerGraphicsFromScratch/js/hooks/extensions/__init__.py
ComputerGraphicsFromScratch/js/hooks/extensions/highlight.js
ComputerGraphicsFromScratch/js/libs/__init__.py
computer_graphics_from_scratch-2024.3.5.0.dist-info/METADATA
computer_graphics_from_scratch-2024.3.5.0.dist-info/WHEEL
computer_graphics_from_scratch-2024.3.5.0.dist-info/entry_points.txt
computer_graphics_from_scratch-2024.3.5.0.dist-info/top_level.txt
computer_graphics_from_scratch-2024.3.5.0.dist-info/RECORD
